xsync/__init__.py
xsync/deco.py
xsync/errors.py
xsync/hybrid.py
xsync/py.typed
xsync/types.py
xsync/utils.py
xsync-0.2.1.dist-info/LICENSE
xsync-0.2.1.dist-info/METADATA
xsync-0.2.1.dist-info/WHEEL
xsync-0.2.1.dist-info/top_level.txt
xsync-0.2.1.dist-info/RECORD
